{
  "schema_version": 1,
  "program": {
    "key": "taskmaster",
    "name": "TaskMaster",
    "category": "Apps",
    "description": "A stateless, anonymous item exchange kiosk for ComputerCraft",
    "source_root": "Apps/TaskMaster",
    "entrypoint": "taskmaster.lua",
    "version": "1.0.21"
  },
  "build": {
    "commit": "5c287cf4c4dc9be7ab55c42dbc8eb9279978d5ad",
    "generated_at": "2026-04-14T04:28:02Z",
    "package_hash": "bd1a25c568b11d3969d6fcea91796bda578aeec2ec5552a05c28a67fda7c5048"
  },
  "install": {
    "preserve": [],
    "files": [
      {
        "repo_path": "System/runtime_startup.lua",
        "install_path": "startup.lua",
        "sha256": "0f3d5ad9ccbcf490f8d4e1dceaa5c02b080516965e5aa585745b23b775248ef7"
      },
      {
        "repo_path": "System/roger_logs.lua",
        "install_path": "rogerlogs.lua",
        "sha256": "6ecff86686f77a1d5255013f98c986493b8f4c7e1347ef3139441f7726338428"
      },
      {
        "repo_path": "System/roger_update.lua",
        "install_path": "rogerupdate.lua",
        "sha256": "d5b69aa035dc58d3882cb43094bf85f40f7d8f7e1d1542dd68f31dcf513047ed"
      },
      {
        "repo_path": "Shared/lib/roger_supervisor.lua",
        "install_path": "lib/roger_supervisor.lua",
        "sha256": "82a718c570d79d46a905f5f09b734621d44f0f30afe38e52c284a0306bc5c363"
      },
      {
        "repo_path": "Shared/lib/roger_logging.lua",
        "install_path": "lib/roger_logging.lua",
        "sha256": "a73913a74cad2ce561025c4007b5330f2e7f6ded93c9b572c34938a2f4aca8b6"
      },
      {
        "repo_path": "Shared/lib/updater.lua",
        "install_path": "lib/updater.lua",
        "sha256": "a960f29ff3fc89d6368f780117b2a8149cc3f9157d3bb648f7f20c510a9b6196"
      },
      {
        "repo_path": "Apps/TaskMaster/taskmaster.lua",
        "install_path": "taskmaster.lua",
        "sha256": "e53296e83befcec4c6628accb753e5fc5ffae3036dc08975f11011d2fa759f98"
      },
      {
        "repo_path": "Shared/lib/monitor_scale.lua",
        "install_path": "lib/monitor_scale.lua",
        "sha256": "d1686cc3ad8f58937cfd70e1fb5b5e701002478c24c4c185652f9e8d9851b7c8"
      }
    ]
  },
  "runtime": {
    "boot_mode": "supervisor",
    "system_entrypoint": "startup.lua",
    "app_entrypoint": "taskmaster.lua",
    "auto_restart": true,
    "update_interval": 60,
    "requires_updater": true,
    "lib_modules": [
      "lib.monitor_scale",
      "lib.roger_logging"
    ]
  }
}